COPYING.txt
MANIFEST.in
README.rst
globster.py
lazy_regex.py
setup.py
globster.egg-info/PKG-INFO
globster.egg-info/SOURCES.txt
globster.egg-info/dependency_links.txt
globster.egg-info/top_level.txt