Metadata-Version: 1.1
Name: globster
Version: 0.1.0
Summary: Convert shell-like globs to regular expressions
Home-page: https://github.com/tsileo/globster
Author: Thomas Sileo
Author-email: thomas.sileo@gmail.com
License: GPLv2
Keywords: some keyword
Platform: UNKNOWN
Classifier: Development Status :: 4 - Beta
Classifier: Intended Audience :: Developers
Classifier: License :: OSI Approved :: GNU General Public License v2 (GPLv2)
Classifier: Programming Language :: Python
